ebus/__init__.py
ebus-0.1.3.dist-info/LICENSE
ebus-0.1.3.dist-info/METADATA
ebus-0.1.3.dist-info/WHEEL
ebus-0.1.3.dist-info/top_level.txt
ebus-0.1.3.dist-info/RECORD
