Metadata-Version: 2.1
Name: ebus
Version: 0.1.3
Summary: ebus - Event bus
Home-page: https://github.com/abisxir/ebus
Author: Abi
Author-email: abi@singiro.com
License: MIT
Download-URL: https://github.com/abisxir/ebus/0.1.3.tar.gz
Keywords: event bus
Platform: any
Classifier: Development Status :: 3 - Alpha
Classifier: Programming Language :: Python :: 2.7
Classifier: Programming Language :: Python :: 3.5
